bash2py/__about__.py
bash2py/__init__.py
bash2py/base.py
bash2py/curl.py
bash2py/etcd2.py
bash2py/openssl.py
bash2py/pg.py
bash2py-0.0.1.dist-info/METADATA
bash2py-0.0.1.dist-info/WHEEL
bash2py-0.0.1.dist-info/licenses/LICENCE
bash2py-0.0.1.dist-info/RECORD
